{"assets":{"3F67C469BCD40881DECCE1F37E625394":{"type":"texture","index":1,"assetRequest":{"type":"slide","state":"contents","slide":"none"},"url":{"native":"assets\/2C00E991-63AB-4D58-B3A5-48C4C256AFE3.pdf"},"width":720,"height":405},"75E8D92920A010CDD055E4A3E6A3050F":{"type":"texture","index":0,"assetRequest":{"type":"slide","state":"contents","slide":"none"},"url":{"native":"assets\/2C00E991-63AB-4D58-B3A5-48C4C256AFE3.pdf"},"width":720,"height":405}},"events":[{"effects":[{"beginTime":0,"baseLayer":{"animations":[],"initialState":{"affineTransform":[1,0,0,1,0,0],"masksToBounds":false,"rotation":0,"scale":1,"position":{"pointX":360,"pointY":202.5},"width":720,"sublayerTransform":[1,0,0,0,0,1,0,0,0,0,1,0,0,0,0,1],"contentsRect":{"y":0,"x":0,"width":1,"height":1},"opacity":1,"edgeAntialiasingMask":251658240,"height":405,"hidden":false,"anchorPoint":{"pointX":0.5,"pointY":0.5}},"objectID":"0","layers":[{"animations":[],"initialState":{"affineTransform":[1,0,0,1,0,0],"masksToBounds":false,"rotation":0,"scale":1,"position":{"pointX":360,"pointY":202.5},"width":720,"sublayerTransform":[1,0,0,0,0,1,0,0,0,0,1,-0.00093354433244735948,0,0,0,1],"contentsRect":{"y":0,"x":0,"width":1,"height":1},"opacity":1,"edgeAntialiasingMask":251658240,"height":405,"hidden":false,"anchorPoint":{"pointX":0.5,"pointY":0.5}},"layers":[{"animations":[],"layers":[],"texturedRectangle":{"isBackgroundTexture":false,"singleTextureOpacity":1,"textureType":0,"textBaseline":0,"textXHeight":0,"isVerticalText":false},"initialState":{"affineTransform":[1,0,0,1,0,0],"masksToBounds":false,"rotation":0,"scale":1,"position":{"pointX":360,"pointY":202.5},"width":720,"sublayerTransform":[1,0,0,0,0,1,0,0,0,0,1,0,0,0,0,1],"contentsRect":{"y":0,"x":0,"width":1,"height":1},"opacity":1,"edgeAntialiasingMask":0,"height":405,"hidden":false,"anchorPoint":{"pointX":0.5,"pointY":0.5}},"texture":"3F67C469BCD40881DECCE1F37E625394"},{"animations":[{"additive":false,"timeOffset":0,"beginTime":0,"from":{"scalar":false},"repeatCount":0,"fillMode":"both","duration":0.01,"autoreverses":false,"property":"hidden","to":{"scalar":true},"removedOnCompletion":false}],"layers":[],"texturedRectangle":{"isBackgroundTexture":false,"singleTextureOpacity":1,"textureType":0,"textBaseline":0,"textXHeight":0,"isVerticalText":false},"initialState":{"affineTransform":[1,0,0,1,0,0],"masksToBounds":false,"rotation":0,"scale":1,"position":{"pointX":360,"pointY":202.5},"width":720,"sublayerTransform":[1,0,0,0,0,1,0,0,0,0,1,0,0,0,0,1],"contentsRect":{"y":0,"x":0,"width":1,"height":1},"opacity":1,"edgeAntialiasingMask":0,"height":405,"hidden":false,"anchorPoint":{"pointX":0.5,"pointY":0.5}},"texture":"75E8D92920A010CDD055E4A3E6A3050F"}]}]},"effects":[],"duration":0.01,"type":"transition","attributes":{"direction":0},"name":"none","objectID":"0"}],"automaticPlay":false,"hyperlinks":[{"url":"https:\/\/www.dkms.de\/rund-um-die-spende\/ablauf-der-spende","targetRectangle":{"y":354.67829677439795,"x":362.87402417528347,"width":122.07958984375,"height":13.746020230290014}},{"url":"https:\/\/www.dkms.de\/aktiv-werden\/online-aktionen\/paul","targetRectangle":{"y":218.31027975131792,"x":549.72219982485137,"width":3.05615234375,"height":25.746020230290014}},{"url":"https:\/\/www.dkms.de\/aktiv-werden\/online-aktionen\/paul","targetRectangle":{"y":218.31027975131792,"x":552.77835216860137,"width":93.328125,"height":25.746020230290014}}],"accessibility":[{"text":"Google Shape;54;p13","targetRectangle":{"y":0,"x":0,"width":286.47213745117188,"height":405}},{"text":"Fakten zur Spende","targetRectangle":{"y":292.26967962895787,"x":326.87402298319057,"width":151.140625,"height":22.916576684860047}},{"text":"90% der Spenden können aus der Blutbahn entnommen werden","targetRectangle":{"y":315.18625631381792,"x":362.87402417528347,"width":216.498046875,"height":39.492040460580029}},{"text":"Weitere Infos zum Ablauf","targetRectangle":{"y":354.67829677439795,"x":362.87402417528347,"width":122.07958984375,"height":13.746020230290014}},{"text":"Um was gehts?","targetRectangle":{"y":71.287401360789659,"x":426.3543303744998,"width":124.6943359375,"height":22.916576684860047}},{"text":"Paul aus Stadtroda kämpft seit Ende letzten Jahres um sein Leben und braucht dringend eine Stammzellenspende. Bitte registriert euch bei der DKMS, jede Registrierung erhöht seine Chancen!","targetRectangle":{"y":94.203978045649706,"x":426.3543303744998,"width":253.14501953125,"height":66.984080921160057}},{"text":"Werde Pauls Held:In","targetRectangle":{"y":25.169290914310238,"x":322.94094478802413,"width":183.357421875,"height":25.206762185611296}},{"text":"Google Shape;59;p13","targetRectangle":{"y":225.93110656738281,"x":651.9193115234375,"width":64.651573181152344,"height":56.610237121582031}},{"text":"Google Shape;60;p13","targetRectangle":{"y":324.7952880859375,"x":655.45379638671875,"width":57.582675933837891,"height":54.622047424316406}},{"text":"Wie läuft die Registrierung?","targetRectangle":{"y":195.39370306645787,"x":322.94094863275848,"width":225.59033203125,"height":22.916576684860047}},{"text":"Die Registrierung geht einfach über die Website der DKMS","targetRectangle":{"y":218.31027975131792,"x":358.94094982485137,"width":287.16552734375,"height":25.746020230290014}},{"text":"Ihr bekommt ein Testset mit den Stäbchen nach Hause und schickt die Proben zurück an DKMS","targetRectangle":{"y":244.05629998160794,"x":358.94094982485137,"width":291.46240234375,"height":27.492040460580029}},{"text":"Google Shape;61;p13","targetRectangle":{"y":12.974409103393555,"x":642.60809326171875,"width":63.661575317382812,"height":26.738189697265625}},{"text":"Google Shape;62;p13","targetRectangle":{"y":75.271652221679688,"x":321.63778686523438,"width":83.854255676269531,"height":85.133857727050781}}],"baseLayer":{"animations":[],"initialState":{"affineTransform":[1,0,0,1,0,0],"masksToBounds":false,"rotation":0,"scale":1,"position":{"pointX":360,"pointY":202.5},"width":720,"sublayerTransform":[1,0,0,0,0,1,0,0,0,0,1,0,0,0,0,1],"contentsRect":{"y":0,"x":0,"width":1,"height":1},"opacity":1,"edgeAntialiasingMask":251658240,"height":405,"hidden":false,"anchorPoint":{"pointX":0.5,"pointY":0.5}},"objectID":"0","layers":[{"animations":[],"initialState":{"affineTransform":[1,0,0,1,0,0],"masksToBounds":false,"rotation":0,"scale":1,"position":{"pointX":360,"pointY":202.5},"width":720,"sublayerTransform":[1,0,0,0,0,1,0,0,0,0,1,-0.00093354433244735948,0,0,0,1],"contentsRect":{"y":0,"x":0,"width":1,"height":1},"opacity":1,"edgeAntialiasingMask":251658240,"height":405,"hidden":false,"anchorPoint":{"pointX":0.5,"pointY":0.5}},"layers":[{"animations":[],"layers":[],"texturedRectangle":{"isBackgroundTexture":false,"singleTextureOpacity":1,"textureType":0,"textBaseline":0,"textXHeight":0,"isVerticalText":false},"initialState":{"affineTransform":[1,0,0,1,0,0],"masksToBounds":false,"rotation":0,"scale":1,"position":{"pointX":360,"pointY":202.5},"width":720,"sublayerTransform":[1,0,0,0,0,1,0,0,0,0,1,0,0,0,0,1],"contentsRect":{"y":0,"x":0,"width":1,"height":1},"opacity":1,"edgeAntialiasingMask":0,"height":405,"hidden":false,"anchorPoint":{"pointX":0.5,"pointY":0.5}},"texture":"75E8D92920A010CDD055E4A3E6A3050F"}]}]}}]}